twist_moe/cryptojs_aes_port.py
twist_moe/pkcs7.py
twist_moe/tui.py
twist_moe/twist_api.py
twist_moe-1.2.1.dist-info/entry_points.txt
twist_moe-1.2.1.dist-info/WHEEL
twist_moe-1.2.1.dist-info/METADATA
twist_moe-1.2.1.dist-info/RECORD
