Metadata-Version: 2.1
Name: twist-moe
Version: 1.2.1
Summary: twist.moe client
Author: witherornot
Author-email: damemem@gmail.com
Requires-Python: >=3.6,<4.0
Classifier: Programming Language :: Python :: 3
Classifier: Programming Language :: Python :: 3.6
Classifier: Programming Language :: Python :: 3.7
Classifier: Programming Language :: Python :: 3.8
Classifier: Programming Language :: Python :: 3.9
Requires-Dist: pycryptodome
Requires-Dist: requests
Requires-Dist: windows-curses; sys_platform == "win32"
